langchain_teradata/__init__.py
langchain_teradata/vector_store.py
langchain_teradata/common/__init__.py
langchain_teradata/common/utils.py
langchain_teradata/telemetry_utils/__init__.py
langchain_teradata/telemetry_utils/queryband.py
langchain_teradata/utils/__init__.py
langchain_teradata/utils/document_utils.py
langchain_teradata-20.0.0.1.dist-info/LICENSE-3RD-PARTY.pdf
langchain_teradata-20.0.0.1.dist-info/LICENSE.pdf
langchain_teradata-20.0.0.1.dist-info/METADATA
langchain_teradata-20.0.0.1.dist-info/WHEEL
langchain_teradata-20.0.0.1.dist-info/top_level.txt
langchain_teradata-20.0.0.1.dist-info/zip-safe
langchain_teradata-20.0.0.1.dist-info/RECORD
