Metadata-Version: 2.1
Name: langchain-teradata
Version: 20.0.0.1
Summary: Teradata package for langchain
Home-page: https://teradata.com
Author: Teradata Corporation
License: Teradata License Agreement
Keywords: Teradata
Platform: MacOS X, Windows, Linux
Classifier: Programming Language :: Python :: 3 :: Only
Classifier: Programming Language :: Python :: 3.9
Classifier: Operating System :: Microsoft :: Windows
Classifier: Operating System :: MacOS :: MacOS X
Classifier: Operating System :: POSIX :: Linux
Classifier: Topic :: Database :: Front-Ends
Classifier: License :: Other/Proprietary License
Requires-Python: >=3.9
License-File: LICENSE-3RD-PARTY.pdf
License-File: LICENSE.pdf
Requires-Dist: langchain-core (>=0.3.72)
Requires-Dist: teradatagenai (>=20.00.00.04)
